blob_dict/__init__.py
blob_dict/py.typed
blob_dict/blob/__init__.py
blob_dict/blob/audio.py
blob_dict/blob/audio_video.py
blob_dict/blob/image.py
blob_dict/blob/json.py
blob_dict/blob/video.py
blob_dict/dict/__init__.py
blob_dict/dict/git.py
blob_dict/dict/multi_replica.py
blob_dict/dict/path.py
blob_dict/dict/proxy.py
blob_dict/dict/valkey.py
blob_dict-0.1.16.dist-info/METADATA
blob_dict-0.1.16.dist-info/WHEEL
blob_dict-0.1.16.dist-info/licenses/LICENSE
blob_dict-0.1.16.dist-info/RECORD
