Metadata-Version: 2.4
Name: blob-dict
Version: 0.1.16
Project-URL: Repository, https://github.com/chuanconggao/BlobDict/
License-Expression: MIT
License-File: LICENSE
Requires-Python: >=3.12
Requires-Dist: cachetools>=6.1.0
Requires-Dist: extratools-core>=0.1.28
Requires-Dist: pydantic>=2.10.6
Requires-Dist: pyyaml>=6.0.2
Requires-Dist: simple-zstd>=0.1.0
Provides-Extra: audio
Requires-Dist: moviepy>=2.0.0; extra == 'audio'
Requires-Dist: soundfile>=0.13.1; extra == 'audio'
Provides-Extra: git
Requires-Dist: extratools-git>=0.1.3; extra == 'git'
Provides-Extra: image
Requires-Dist: extratools-image>=0.1.6; extra == 'image'
Provides-Extra: s3
Requires-Dist: cloudpathlib[s3]>=0.21.0; extra == 's3'
Provides-Extra: valkey
Requires-Dist: valkey[libvalkey]>=6.1.0; extra == 'valkey'
Provides-Extra: video
Requires-Dist: moviepy>=2.0.0; extra == 'video'
